MANIFEST.in
README.md
setup.py
catsql/__init__.py
catsql/cmdline.py
catsql/database.py
catsql/filter.py
catsql/main.py
catsql/nullify.py
catsql/patch.py
catsql.egg-info/PKG-INFO
catsql.egg-info/SOURCES.txt
catsql.egg-info/dependency_links.txt
catsql.egg-info/entry_points.txt
catsql.egg-info/requires.txt
catsql.egg-info/top_level.txt
catsql/daffsql/__init__.py
catsql/daffsql/dictify.py
catsql/daffsql/sqlalchemy_database.py
catsql/daffsql/sqlalchemy_helper.py